LICENSE
MANIFEST.in
README.md
setup.py
epyper/__init__.py
epyper/bsp.py
epyper/demo.py
epyper/displayCOGProcess.py
epyper/displayController.py
epyper/displayHardwareDriver.py
epyper/enum.py
epyper.egg-info/PKG-INFO
epyper.egg-info/SOURCES.txt
epyper.egg-info/dependency_links.txt
epyper.egg-info/not-zip-safe
epyper.egg-info/requires.txt
epyper.egg-info/top_level.txt
epyper/samples/eaLogo.png
epyper/samples/pdLogo.png