Metadata-Version: 1.1
Name: epyper
Version: 0.1.0
Summary: Python driver for Embedded Artists 2.7 inch E-paper Display Module
Home-page: https://github.com/mnowotka/epyper
Author: Michal Nowotka
Author-email: mmmnow@gmail.com
License: MIT
Platform: UNKNOWN
Classifier: Development Status :: 4 - Beta
Classifier: Environment :: Handhelds/PDA's
Classifier: Intended Audience :: Developers
Classifier: License :: OSI Approved :: MIT License
Classifier: Operating System :: POSIX :: Linux
Classifier: Programming Language :: Python :: 2.7
Classifier: Topic :: Multimedia :: Video :: Display
